{
	"locales": [
		{
			"languages": [
				"en",
				"en-GB"
			],
			"intl": "en-GB",
			"fileNames": "en"
		},
		{
			"languages": [
				"fr",
				"fr-FR"
			],
			"intl": "fr-FR",
			"fileNames": "fr"
		}
	],
	"modules": [
 {
            "name": "CoreModule",
            "npm": "https://github.com/openimis/openimis-fe-core_js.git"
        },
            {
            "name": "HomeModule",
            "npm": "https://github.com/openimis/openimis-fe-home_js.git"
        },
            {
            "name": "LocationModule",
            "npm": "https://github.com/openimis/openimis-fe-location_js.git"
        },
            {
            "name": "InsureeModule",
            "npm": "https://github.com/openimis/openimis-fe-insuree_js.git"
        },
            {
            "name": "MedicalModule",
            "npm": "https://github.com/openimis/openimis-fe-medical_js.git"
        },
            {
            "name": "MedicalPriceListModule",
            "npm": "https://github.com/openimis/openimis-fe-medical_pricelist_js.git"
        },
            {
            "name": "ProductModule",
            "npm": "https://github.com/openimis/openimis-fe-product_js.git"
        },
            {
            "name": "PolicyModule",
            "npm": "https://github.com/openimis/openimis-fe-policy_js.git"
        },
            {
            "name": "PayerModule",
            "npm": "https://github.com/openimis/openimis-fe-payer_js.git"
        },
            {
            "name": "ContributionModule",
            "npm": "https://github.com/openimis/openimis-fe-contribution_js.git"
        },
            {
            "name": "PaymentModule",
            "npm": "https://github.com/openimis/openimis-fe-payment_js.git"
        },
            {
            "name": "ClaimModule",
            "npm": "https://github.com/openimis/openimis-fe-claim_js.git"
        },
            {
            "name": "ClaimBatchModule",
            "npm": "https://github.com/openimis/openimis-fe-claim_batch_js.git"
        },
            {
            "name": "AdminModule",
            "npm": "https://github.com/openimis/openimis-fe-admin_js.git"
        },
            {
            "name": "ToolsModule",
            "npm": "https://github.com/openimis/openimis-fe-tools_js.git"
        },
            {
            "name": "ProfileModule",
            "npm": "https://github.com/openimis/openimis-fe-profile_js.git"
        },
            {
            "name": "LanguageFrModule",
            "npm": "https://github.com/openimis/openimis-fe-language_fr_js.git"
        },
            {
            "name": "CalculationModule",
            "npm": "https://github.com/openimis/openimis-fe-calculation_js.git"
        },
            {
            "name": "PolicyHolderModule",
            "npm": "https://github.com/openimis/openimis-fe-policyholder_js.git"
        },
            {
            "name": "ContributionPlanModule",
            "npm": "https://github.com/openimis/openimis-fe-contribution_plan_js.git"
        },
            {
            "name": "ContractModule",
            "npm": "https://github.com/openimis/openimis-fe-contract_js.git"
        },
            {
            "name": "InvoiceModule",
            "npm": "https://github.com/openimis/openimis-fe-invoice_js.git"
        }
	]
}
